cell_toolbar/__init__.py
cell_toolbar/_version.py
cell_toolbar-0.2.2.data/data/share/jupyter/labextensions/cell_toolbar/build_log.json
cell_toolbar-0.2.2.data/data/share/jupyter/labextensions/cell_toolbar/package.json
cell_toolbar-0.2.2.data/data/share/jupyter/labextensions/cell_toolbar/static/09663a36fc05e7190af8.ttf
cell_toolbar-0.2.2.data/data/share/jupyter/labextensions/cell_toolbar/static/2bccecf0bc7e96cd5ce4.woff2
cell_toolbar-0.2.2.data/data/share/jupyter/labextensions/cell_toolbar/static/3a8924cd5203a2862871.woff2
cell_toolbar-0.2.2.data/data/share/jupyter/labextensions/cell_toolbar/static/4d4a2d7fd1c6684845cb.woff2
cell_toolbar-0.2.2.data/data/share/jupyter/labextensions/cell_toolbar/static/5656d596bc597165a421.ttf
cell_toolbar-0.2.2.data/data/share/jupyter/labextensions/cell_toolbar/static/5d02dc9b858e3c85a794.ttf
cell_toolbar-0.2.2.data/data/share/jupyter/labextensions/cell_toolbar/static/9fc85f3a4544ab0d570c.woff2
cell_toolbar-0.2.2.data/data/share/jupyter/labextensions/cell_toolbar/static/fbbf06d7437aa30f3cd4.ttf
cell_toolbar-0.2.2.data/data/share/jupyter/labextensions/cell_toolbar/static/lib_index_js.07189b54d37eecc2f2a0.js
cell_toolbar-0.2.2.data/data/share/jupyter/labextensions/cell_toolbar/static/lib_index_js.07189b54d37eecc2f2a0.js.map
cell_toolbar-0.2.2.data/data/share/jupyter/labextensions/cell_toolbar/static/lib_index_js.4d12fe590f03feb1e65d.js
cell_toolbar-0.2.2.data/data/share/jupyter/labextensions/cell_toolbar/static/lib_index_js.4d12fe590f03feb1e65d.js.map
cell_toolbar-0.2.2.data/data/share/jupyter/labextensions/cell_toolbar/static/lib_index_js.f14db2547d2394c97ba7.js
cell_toolbar-0.2.2.data/data/share/jupyter/labextensions/cell_toolbar/static/lib_index_js.f14db2547d2394c97ba7.js.map
cell_toolbar-0.2.2.data/data/share/jupyter/labextensions/cell_toolbar/static/remoteEntry.1308823964e5e13ba656.js.map
cell_toolbar-0.2.2.data/data/share/jupyter/labextensions/cell_toolbar/static/remoteEntry.3555af4fdf91da7df3f5.js
cell_toolbar-0.2.2.dist-info/METADATA
cell_toolbar-0.2.2.dist-info/WHEEL
cell_toolbar-0.2.2.dist-info/licenses/LICENSE
cell_toolbar-0.2.2.dist-info/RECORD
