Metadata-Version: 2.1
Name: cell_toolbar
Version: 0.2.2
Summary: A JupyterLab extension that gives each cell a toolbar with functions to hide/show code, run code, etc.
Project-URL: Homepage, https://github.com/LtStarbuck1030/cell_toolbar
Project-URL: Bug Tracker, https://github.com/LtStarbuck1030/cell_toolbar/issues
Project-URL: Repository, https://github.com/LtStarbuck1030/cell_toolbar.git
Author-email: Lisa Marie Meyers <lisamarie9006@gmail.com>
License: BSD 3-Clause License
License-File: LICENSE
Classifier: Framework :: Jupyter
Classifier: Framework :: Jupyter :: JupyterLab
Classifier: Framework :: Jupyter :: JupyterLab :: 4
Classifier: Framework :: Jupyter :: JupyterLab :: Extensions
Classifier: Framework :: Jupyter :: JupyterLab :: Extensions :: Prebuilt
Classifier: License :: OSI Approved :: BSD License
Classifier: Programming Language :: Python
Classifier: Programming Language :: Python :: 3
Classifier: Programming Language :: Python :: 3.8
Classifier: Programming Language :: Python :: 3.9
Classifier: Programming Language :: Python :: 3.10
Classifier: Programming Language :: Python :: 3.11
Requires-Python: >=3.8
